Workbook

Sheet ReadMe
A1: Funding programmes database for the SME financing agent (Masar Team, Dormathon 2026).
A2: Compiled 10 Oct 2026 by web research. Each row was filled ONLY from the page in 'Official / source URL'.
A3: 'not stated' = the source page did not publish that field. Do not let the agent invent it; it should say 'confirm with agency'.
A4: Yellow 'Verify flag' = secondary/news source, old source, or conflicting official dates. Check before the demo if the row is used on stage.
A5: Deadline date + Days left (formula) are filled only where an explicit date was published.
A6: BNM SME SRF end date resolved: BNM's FAQ (latest update 9 Oct 2026), brochure and funds page all say 30 Jun 2027 (the 15 May 2026 FAQ said 31 Dec 2026).
A7: Rates quoted as 'flat' are charged on the original principal; effective annual rate is roughly 1.8x the flat rate over multi-year tenures.
A8: This DB covers 20 programmes; the Entrepreneur Development Ministry says ~140 schemes exist (The Star, 1 Aug 2026). Say '20 of ~140' in the pitch, not 'all'.
A9: Not legal or financial advice. Eligibility is decided by the agency/bank.

Sheet Programs
A1: ID | B1: Programme | C1: Agency | D1: Type | E1: Min (RM) | F1: Max (RM) | G1: Rate / cost | H1: Tenure | I1: Ownership rule | J1: Bumi only | K1: Women only | L1: Age rule | M1: Min operating period | N1: Min turnover | O1: Other eligibility | P1: Sectors | Q1: Required documents | R1: Deadline (as stated) | S1: Deadline date | T1: Days left | U1: Status | V1: How to apply | W1: Official / source URL | X1: Source type | Y1: Verify flag | Z1: Notes | AA1: Checked on
A2: TEKUN-NIAGA | B2: TEKUN Niaga (SPM / SPK / SPS) | C2: TEKUN Nasional | D2: Microfinance loan | E2: 10001 | F2: 100000 | G2: 4% of financing value per year (flat, for the whole tenure) + savings of 5% of financing value per year | H2: Up to 10 years (SPM and SPK up to 5 yrs; SPS up to 10 yrs) | I2: Malaysian citizen, Bumiputera; companies 100% Bumiputera-owned | J2: Y | K2: N | L2: 18-65 at application; financing must end by 65 | M2: not stated (application form covers both existing and new businesses) | N2: not stated | O2: Bumiputera Malaysian citizen; not bankrupt; companies 100% Bumiputera- and Malaysian-owned; valid PBT licence/permit or SSM registration; fixed, mobile or online business location; owner directly involved full- or part-time; one financing per household; paid-up capital ≤ RM300k; Shariah-compliant activity; group financing takaful mandatory; SKSPS self-employed social security mandatory for year 1. First financing: SPK RM10,001–50,000 or SPS RM50,001–100,000; SPM RM1,000–10,000 is for repeat/overlapping financing only | P2: All Shariah-compliant | Q2: Copy of IC of applicant and spouse if applicable (front and back); PBT licence/permit or SSM business registration; photos showing the business in operation; latest 3 months savings/current account bank statements showing applicant/company name, bank name and account number; additional documents if applicable | R2: Ongoing (no deadline stated) | T2: =IF(S2="","",S2-TODAY()) | U2: Open (ongoing scheme) | V2: TEKUN branch counter near the business, or TEKUN Online (tekunonline.tekun.gov.my); 03-9059 8888 | W2: https://www.tekun.gov.my/?page_id=281 | X2: Official (TEKUN Niaga 'Syarat-syarat' page, updated 28 Nov 2025) | Z2: Old source URL (English conditions page) now returns 404. That page said age 18–60, ≥20% own cash for new businesses and other business financing ≤ RM100k; the current official page does not list those conditions. Rates are flat on original principal, so effective rate is higher (RinggitPlus, Jun 2026). One-time wakalah fee from RM50 to RM500 depending on amount. | AA2: 46305
A3: TEKUN-SPOT | B3: TEKUN SPOT (online businesses) | C3: TEKUN Nasional | D3: Microfinance loan | E3: 1000 | F3: 20000 | G3: 3% p.a. | H3: Up to 5 years | I3: Bumiputera | J3: Y | K3: N | L3: 18-65 | M3: not stated | N3: not stated | O3: For online businesses; cap RM5,000 without SSM registration | P3: Online businesses | Q3: Not listed | R3: Ongoing | T3: =IF(S3="","",S3-TODAY()) | U3: Open (per Jun 2026 article) | V3: Online via TEKUN | W3: https://ringgitplus.com/ms/blog/sudut-pakar/nak-modal-bisnes-ini-perbezaan-tekun-aim-dan-bsn-madani-belia-yang-anda-perlu-tahu.html | X3: Secondary (RinggitPlus, 15 Jun 2026) | Y3: VERIFY on tekun.gov.my | AA3: 46305
A4: AIM-PADURI | B4: PADURI MADANI (AIM) | C4: Amanah Ikhtiar Malaysia | D4: Microfinance loan | E4: 3000 | F4: 30000 | G4: not stated (AIM general: ~10% p.a. per RinggitPlus) | H4: not stated (weekly repayments) | I4: Malaysian | J4: N | K4: Y | L4: 18+ | M4: not stated | N4: not stated | O4: Household income ≤ RM5,880/month or per-capita ≤ RM1,470; no guarantor/collateral; blacklisted/bankrupt applicants accepted. Economic category RM3k–30k; social category up to RM15k | P4: All | Q4: Not published; confirm with AIM | R4: not stated | T4: =IF(S4="","",S4-TODAY()) | U4: Launched 16 May 2026; targets 29,000 women | V4: AIM branch (aim.gov.my) | W4: https://www.malaymail.com/news/malaysia/2026/05/16/pm-launches-paduri-madani-scheme-to-empower-b40-women-entrepreneurs-with-loans-up-to-rm30000/220175 | X4: News (Malay Mail) | Y4: VERIFY on aim.gov.my | Z4: Still unconfirmed: amounts (RM3k–30k economic, up to RM15k social), income test (household ≤ RM5,880/month or per-capita ≤ RM1,470), women-only rule, rate, tenure and documents. All come from news (Malay Mail, RinggitPlus, May 2026) because aim.gov.my refused connections from our network on 2026-10-10 (ports 80 and 443) and no other official page was found. Household-income test needs data the ledger doesn't hold: agent must ask the user. | AA4: 46305
A5: BSN-BELIA | B5: BSN Micro/i Madani Belia | C5: Bank Simpanan Nasional | D5: Microfinance loan | E5: 2000 | F5: 100000 | G5: 3.50%–4.00% p.a. flat | H5: 1–7 years | I5: Malaysian-owned; ≥51% owned/operated by youth ≤ 30 | J5: N | K5: N | L5: Youth owner ≤ 30 | M5: 6 months | N5: not stated | O5: Micro enterprise; registered with SSM / local authority / professional body | P5: All | Q5: IC of owners/partners/directors; business registration or PBT licence; latest 6 months bank statements; premises electricity & water bills; others on request | R5: not stated | T5: =IF(S5="","",S5-TODAY()) | U5: Open (no closing date published) | V5: BSN Micro Finance Centre / state main branch / online; reply within 6 working days; 03-2613 1900 | W5: https://www.bsn.com.my/cms/upload/pdf/business/madani/faq/madani_belia.pdf | X5: Official (FAQ PDF) | Z5: Reported to CCRIS. | AA5: 46305
A6: MSME-DIGITAL | B6: MSME Digital Grant MADANI | C6: BSN (disbursing) / MDEC (solution panel) / MOF | D6: Matching grant | E6: 0 | F6: 5000 | G6: Grant: up to 50% of invoice, max RM5,000 | H6: n/a | I6: ≥60% Malaysian citizens | J6: N | K6: N | L6: n/a | M6: 6 months | N6: RM50,000 average annual | O6: Up to 3 digital services from MDEC-appointed providers (e-POS, HR/CRM, digital marketing, cybersecurity, ERP/accounting & tax, digital signature, IoT, AI, e-invoice); not for SMEs that already received an earlier Digitalisation Matching Grant (except for e-invoice services); subject to allocation | P6: All | Q6: Copy of IC or passport of owner/director/partner/appointed representative; copy of SSM (or equivalent) registration; latest audited accounts OR latest management accounts OR last 2 months bank statements; quotation or payment invoice from the appointed service provider; other documents BSN requests | R6: Closed: applications closed effective 6 Sep 2025 (last day 5 Sep 2025) | S6: 45905 | T6: =IF(S6="","",S6-TODAY()) | U6: Closed (official application form); no 2026 round found on BSN or MDEC pages | V6: BSN 'Apply Now' links to the MDEC-appointed Funding Societies form, which is closed | W6: https://bsn.com.my/page/MSMEMadani | X6: Official (BSN page + BSN FAQ Aug 2025 https://www.bsn.com.my/cms/upload/pdf/business/msme_faq_aug_bm.pdf; closure notice on BSN's Apply Now form https://fundingsocieties.com.my/msme-digital-grant-madani) | Z6: Open status resolved: the application form BSN links to says 'applications closed effective 6 Sep 2025 (final day to apply: 5 Sep 2025)' in line with the Joint Committee's instruction. A commercial blog (aitraining2u, Jul 2026) mentions RM150m for SME digitalisation grants under Budget 2026, but no official 2026 round was found; re-check before the demo. If a new round opens, your own product could qualify if it is on the MDEC panel. | AA6: 46305
A7: BNM-SRF | B7: SME Stabilisation Relief Facility (SME SRF) | C7: Bank Negara Malaysia via participating FIs; guarantee by CGC/SJPP | D7: Concessionary loan (BNM Fund for SMEs) | E7: 0 | F7: 750000 | G7: Max 3.75% p.a. incl. 0.5% guarantee fee | H7: Up to 5 years | I7: ≥51% Malaysian | J7: N | K7: N | L7: n/a | M7: not stated | N7: not stated | O7: Viable but materially affected by trade/supply-chain disruption from the Middle East conflict (since Mar 2026); working capital only; no refinancing; up to 80% guarantee from CGC or SJPP, no collateral; RM750k cap across all banks; open to new and existing bank customers; RM10 billion facility | P7: All | Q7: Bank statements and transaction records; CCRIS account conduct data; audited financial statements or management accounts; sales records, invoices, purchase orders; supplier contracts/correspondence showing cost increases, delays or cancellations; stock movement records; debtor/creditor ageing reports; final list set by each bank | R7: 15 May 2026 to 30 Jun 2027 or until fully utilised (BNM FAQ latest update 9 Oct 2026 and brochure; the 15 May 2026 FAQ said 31 Dec 2026) | S7: 46568 | T7: =IF(S7="","",S7-TODAY()) | U7: Open | V7: Any participating bank / Islamic bank / DFI; decision target 7 business days | W7: https://www.bnm.gov.my/documents/20124/6025157/20261009-FAQ-SRF-EN.pdf | X7: Official (BNM SME SRF FAQ, latest update 9 Oct 2026; also https://www.bnm.gov.my/funds4sme and brochure https://www.bnm.gov.my/documents/20124/6025157/SME-SRF-Brochure-EN-8.pdf) | Z7: Deadline conflict resolved: BNM's FAQ (latest update 9 Oct 2026), brochure and funds page all say 30 Jun 2027; the FAQ now gives a RM10 billion facility (the 15 May 2026 FAQ said RM5 billion). Working capital only, so it cannot fund renovation or equipment capex. Strong demo hook: supplier price-rise invoices ARE the 'impact evidence' BNM lists. | AA7: 46305
A8: BNM-MEF | B8: Micro Enterprises Facility (MEF) / Skim Pembiayaan Mikro | C8: Bank Negara Malaysia via participating FIs | D8: Microfinance loan | E8: 1000 | F8: 100000 | G8: Varies by bank (BNM list as at 27 Jul 2026), e.g. BSN Mikro/i Madani 3.5%/4.0% flat; Bank Islam iTEKAD Maju 4% effective; Bank Rakyat MUsK MEF 6.5% flat | H8: Mostly up to 5–7 years | I8: Malaysian (product-specific) | J8: N | K8: N | L8: ~18–70 depending on product | M8: 6 months to 3 years depending on product | N8: not stated | O8: Microenterprises, social enterprises, professional service providers, self-employed incl. gig workers; no collateral (third-party guarantee may be required) | P8: All | Q8: IC of applicant/owners; proof of business operations (registration/licence/permit); proof of income (usually latest 6 months bank statements, sales records, or Form B/BE with tax receipt); other documents per bank (e.g. Maybank: 2 years audited or management accounts; Bank Islam iTEKAD: application form and utility bill) | R8: Ongoing | T8: =IF(S8="","",S8-TODAY()) | U8: Open | V8: Participating FIs (BNM list as at 27 Jul 2026): Agrobank, Alliance, AmBank, Bank Islam, Bank Muamalat, Bank Rakyat, BSN, CIMB Islamic, Maybank, Public Bank, RHB (+ UOB) | W8: https://www.bnm.gov.my/microfinance | X8: Official | Z8: Range of effective rates is wide (AmBank 13.5–18% effective). Agent should rank by effective rate. BSN Mikro/i Madani has a Madani Wanita variant for women entrepreneurs. Documents differ by bank; the bnm.gov.my/microfinance page lists each bank's own list. | AA8: 46305
A9: BNM-PTF | B9: PENJANA Tourism Financing (PTF) | C9: Bank Negara Malaysia via participating FIs; SJPP guarantee | D9: Concessionary loan | E9: 0 | F9: 500000 | G9: not stated on page | H9: not stated on page | I9: SME | J9: N | K9: N | L9: n/a | M9: not stated | N9: not stated | O9: Tourism sectors/activities listed under National Tourism Policy 2020–2030; for expansion/investment (Visit Malaysia Year 2026) | P9: Tourism | Q9: See brochure/FAQ on BNM page | R9: not stated | T9: =IF(S9="","",S9-TODAY()) | U9: Open | V9: Participating FIs | W9: https://www.bnm.gov.my/funds4sme | X9: Official | Z9: A neighbourhood kopitiam is unlikely to qualify unless tourism-linked. | AA9: 46305
A10: BNM-RAFT | B10: Relief and Adaptation Facility (RAFt) | C10: Bank Negara Malaysia via participating FIs | D10: Concessionary loan | E10: 0 | F10: 1000000 | G10: not stated on page | H10: not stated on page | I10: SME | J10: N | K10: N | L10: n/a | M10: not stated | N10: not stated | O10: Relief financing after major floods; adaptation financing (flood protection) anytime; up to RM1m each | P10: All | Q10: See brochure/FAQ on BNM page | R10: Adaptation: anytime | T10: =IF(S10="","",S10-TODAY()) | U10: Open | V10: Participating FIs | W10: https://www.bnm.gov.my/funds4sme | X10: Official | Z10: Replaced Disaster Relief Facility in Aug 2025. | AA10: 46305
A11: CGC-BIZMULA | B11: BizMula-i | C11: Credit Guarantee Corporation (CGC), funded by BNM AES Facility | D11: Direct financing | E11: 30000 | F11: 300000 | G11: 7.00% p.a. effective | H11: Up to 5 years | I11: ≥51% Malaysian; PLC/GLC shareholding ≤ 20% | J11: N | K11: N | L11: Key person ≥21 at application, ≤65 at settlement | M11: Less than 4 years in operation (start-ups only) | N11: not stated | O11: Meets SME Corp definition; registered with SSM or equivalent | P11: All | Q11: Application form + supporting documents (list not published on page) | R11: not stated | T11: =IF(S11="","",S11-TODAY()) | U11: Open (no period stated) | V11: Any CGC branch; form downloadable | W11: https://www.cgc.com.my/?p=18289 | X11: Official | AA11: 46305
A12: CGC-BIZWANITA | B12: BizWanita-i | C12: Credit Guarantee Corporation (CGC) | D12: Direct financing | G12: 6.80% p.a. effective | H12: not stated on page | I12: not stated on page | J12: N | K12: Y | L12: not stated | M12: Less than 4 years in operation | N12: not stated | O12: Direct financing for women entrepreneurs | P12: All | Q12: not stated | R12: not stated | T12: =IF(S12="","",S12-TODAY()) | U12: Listed | V12: Contact form on CGC page / CGC Client Service Centre | W12: https://www.cgc.com.my/bizwanita-i | X12: Official (page incomplete) | Y12: VERIFY amount and tenure | Z12: Amount fields empty on official page. | AA12: 46305
A13: SJPP-GGSM4 | B13: Government Guarantee Scheme MADANI 2026 (GGSM4) | C13: Syarikat Jaminan Pembiayaan Perniagaan (SJPP), MOF | D13: Loan guarantee (bank loan) | F13: 20000000 | G13: Bank's BLR/BFR + max 2.0%; guarantee fee 0.5–1.0% p.a. | H13: Up to 7 years | I13: Sole prop: Malaysian citizen; partnerships/LLP majority Malaysian; companies ≥51% Malaysian | J13: N | K13: N | L13: n/a | M13: not stated | N13: not stated | O13: Guarantee up to 80% (MSME focus sectors: Bumiputera, Halal, Tourism, HGHV, other priority sectors) or 70%; working capital or capex, new financing only (no refinancing); government-funded or government-incentivised financing is not eligible for the guarantee; excludes GLCs, MoF Inc., state-owned enterprises, main-board PLCs, civil-servant owners without approval | P13: All | Q13: Not published by SJPP; SJPP FAQ says to provide the documents required by the participating bank. Confirm with SJPP or your bank | R13: 30 Jun 2027 or until fully utilised | S13: 46568 | T13: =IF(S13="","",S13-TODAY()) | U13: Open | V13: Through participating banks; SJPP +603 2096 5000 | W13: https://sjpp.com.my/schemes/government-guarantee-scheme-madani-2026-ggsm-4 | X13: Official (scheme page + GGSM4 brochure Apr 2026 https://sjpp.com.my/images/scheme-brochure/cover2/GGSM4_brochure.pdf) | Z13: MSME limit RM20m; group aggregate RM50m across SJPP schemes. SMEs apply to a participating bank, which forwards the case to SJPP. Guarantee fee 0.5% p.a. where BNM funding to the bank is at 0%, 0.75% for HGHV/focus sectors, 1.0% for others. | AA13: 46305
A14: SJPP-WCGS-W | B14: Working Capital Guarantee Scheme – Women (WCGS-Women) | C14: SJPP | D14: Loan guarantee | E14: 100000 | F14: 1000000 | G14: Guarantee fee 0.75% p.a. (2% rebate no longer available) | H14: not stated | I14: Malaysian | J14: N | K14: Y | L14: n/a | M14: not stated | N14: not stated | O14: Guarantee cover 80%; sibling schemes: WCGS (RM100k–10m, 70%), WCGS-Bumiputera (RM100k–3m, 80%), WCGS-Start Up (RM100k–500k, 70%) | P14: All | Q14: via bank | R14: not stated | T14: =IF(S14="","",S14-TODAY()) | U14: Listed; 2026 open status not confirmed on page | V14: Participating banks | W14: https://www.sjpp.com.my/ | X14: Official (home page table) | Y14: VERIFY still open in 2026 | AA14: 46305
A15: MARA-SEMAI | B15: MARA DanaNITA (women) / SEMAi (IPMa graduates) / PUTRA (youth) | C15: Majlis Amanah Rakyat (MARA) | D15: Business loan | F15: 150000 | G15: DanaNITA 3.5% profit rate; SEMAi 4%; basis (flat or reducing) not stated | H15: DanaNITA 1–10 years (12–120 months); SEMAi 1–5 years | I15: Bumiputera Malaysian citizen; DanaNITA: majority 51% shareholding by women | J15: Y | K15: DanaNITA: Y | L15: DanaNITA 18–60; SEMAi 18–50; PUTRA ≤40 | M15: DanaNITA: 6 months | N15: not stated | O15: DanaNITA (up to RM150k, Bumiputera women expanding a business): SSM registration; business premises (except online businesses); PBT licence/permit (waived for ≤ RM50k); full-time business; active savings account for latest 6 months; experience/knowledge in the business; Shariah-compliant; not on MARA blacklist; scope = working capital, machines and equipment; no guarantor/collateral for ≤ RM50k, above that a guarantor, land collateral or 10% fixed deposit; grace period up to 12 months. SEMAi (RM10k–50k, 4%) is only for MARA education institution (IPMa) graduates and covers premises renovation. PUTRA: youth ≤40, up to RM10k. SPiM: Bumiputera capacity/expansion up to RM500k. SPiKE: contractors, up to RM1m | P15: All Shariah-compliant (SPiKE: contractors) | Q15: No full checklist published (applications via MyUsahawan login). Items named in DanaNITA conditions: SSM registration; PBT licence/permit (waived ≤ RM50k); bank statements for 3 months (online statements accepted); quotation for renovation or machinery (waived ≤ RM50k); guarantor, land collateral or fixed-deposit documents if > RM50k. Confirm full list with MARA | R15: not stated (ongoing) | T15: =IF(S15="","",S15-TODAY()) | U15: Listed on mara.gov.my | V15: Online via MyUsahawan (myusahawan.mara.gov.my) or MARA district office; MARA hotline 03-2613 2000 | W15: https://www.mara.gov.my/bm/menu_keusahawanan/kemudahan-sokongan/pembiayaan-perniagaan-2/dananita/ | X15: Official (mara.gov.my DanaNITA page; SEMAi page https://www.mara.gov.my/bm/menu_keusahawanan/kemudahan-sokongan/pembiayaan-perniagaan-2/semai/; scheme list https://www.mara.gov.my/bm/menu_keusahawanan/kemudahan-sokongan/pembiayaan-perniagaan-2/) | Z15: Correction: the 2023 brochure mapping was wrong. On mara.gov.my, SEMAi is for IPMa graduates (max RM50k) and the Bumiputera-women scheme up to RM150k is DanaNITA. ID kept as MARA-SEMAI so existing links work. DanaNITA scope lists working capital and machines/equipment, not renovation. Pages carry no update date (site copyright 2025). | AA15: 46305
A16: PUNB-GROW | B16: PROSPER GROW | C16: Perbadanan Usahawan Nasional Berhad (PUNB) | D16: Term financing | F16: 1000000 | G16: 3.5% p.a. flat | H16: Up to 7 years | I16: Sole prop/partnership/LLP 100% Bumiputera; Sdn Bhd ≥51% Bumiputera | J16: Y | K16: N | L16: not stated | M16: 18 months | N16: RM300,000 annual | O16: Max RM500k (sole prop/partnership/LLP), RM1m (Sdn Bhd); retail, distributive trade, manufacturing targeted; excludes agriculture, mining, property, financial services; term + business premises takaful mandatory; personal guarantee required | P16: Retail, distributive trade, manufacturing (others allowed with exclusions) | Q16: PDP form (on PUNB online portal); latest IC copies of applicant and directors; passport-size photos of applicant and directors; SSM search printed within 2 months; photos of existing/proposed premises and products; valid tenancy agreement (if applicable); current-year management account and/or latest 2 years audited accounts; latest 6 months bank statements; quotations per project cost | R16: not stated | T16: =IF(S16="","",S16-TODAY()) | U16: Open (2026 PDS) | V16: PUNB entrepreneur portal: entreportal.punb.com.my | W16: https://www.punb.com.my/wp-content/uploads/2026/04/2026-PDS-PROSPER-GROW-BI.pdf | X16: Official (Product Disclosure Sheet, Apr 2026) | Z16: Document list is PDS section 12; PUNB may ask for more during credit assessment. | AA16: 46305
A17: AGRO-PENJAJA | B17: Agro Penjaja-i | C17: Agrobank (with GPPPKMM hawkers' association) | D17: Membership initiative: micro financing + Cashline-i + Ar-Rahnu | E17: 1000 | F17: 100000 | G17: Micro financing via MRP 2.0 (the related product named in the T&C): from 4.75% p.a. on monthly rest; Cashline-i: BFR + 2.5% p.a. | H17: MRP 2.0 up to 7 years (84 months); Cashline-i up to 5 years (annual review) | I17: Individuals or non-individuals registered as SMEs and below; Malaysian citizen (MRP 2.0, Cashline-i) | J17: N | K17: N | L17: 21 at application to 70 at end of financing (MRP 2.0, Cashline-i) | M17: 12 months (MRP 2.0, Cashline-i) | N17: not stated | O17: Join by opening an Agro Tani Saudagar-i (individual) or Agro Perdana Saudagar-i (non-individual) account; existing Agrobank micro/hawker customers join automatically; Shariah-compliant business. MRP 2.0 (RM1k–100k): micro enterprise per SME Corp definition; no collateral; covers operating costs and purchase or development of fixed assets; refinancing allowed. Also Cashline-i RM1k–5k and Ar-Rahnu up to RM300k | P17: Hawkers / micro F&B and other Shariah-compliant micro businesses (MRP 2.0 focuses on the food production value chain) | Q17: Membership account (individual): MyKad; valid PBT business licence. Micro financing (MRP 2.0): completed application form; copy of IC (and joint applicant's, if any); latest 12 months savings account statements or sales records; copy of business registration or licence (fixed premises); any accepted proof of income | R17: not stated (ongoing) | T17: =IF(S17="","",S17-TODAY()) | U17: Open (product page live; T&C and FAQ dated May 2026; nationwide with GPPPKMM from Jul 2026) | V17: Any Agrobank branch (individual account can also be opened online); 1-300-88-2476 | W17: https://www.agrobank.com.my/product/agro-penjaja-i/ | X17: Official (Agrobank product page + programme T&C and FAQ PDFs, May 2026; MRP 2.0 page https://www.agrobank.com.my/product/microenterprise-special-relief/) | Z17: Most F&B-specific scheme in the DB. Membership gives access to offers; each financing still needs its own approval. T&C section 2 names MRP 2.0 as the related micro-financing product. agrobank.com.my serves an incomplete TLS certificate chain, so some automated fetchers fail on it. | AA17: 46305
A18: SMEBANK-TECHAD | B18: Technology Adoption Fund (TECHAD) | C18: SME Bank | D18: Term financing | E18: 100000 | F18: 10000000 | G18: Up to BFR + 2.5% p.a. | H18: Up to 10 yrs (assets) / 5 yrs (working capital) | I18: ≥51% Malaysian residents; PLC/GLC ≤ 20% | J18: N | K18: N | L18: n/a | M18: 2 years | N18: not stated | O18: MSME per SME Corp; Shariah-compliant; for digitalisation/automation; margin up to 80% (assets) / 100% (WC) | P18: All | Q18: Not listed; see PDS | R18: not stated | T18: =IF(S18="","",S18-TODAY()) | U18: Open | V18: mySME Bank portal (mysmebank.com.my); 03-2603 7700 | W18: https://www.smebank.com.my/technology-adoption-fund-techad | X18: Official | Z18: RM100k minimum is oversized for a micro café. | AA18: 46305
A19: CRADLE-SPRINT | B19: CIP Sprint | C19: Cradle Fund | D19: Conditional grant | F19: 600000 | G19: Convertible commercialisation grant (repayable if terminated) | H19: Up to 18 months | I19: ≥51% Malaysian (or majority Malaysian staff); no entity ≥25% | J19: N | K19: N | L19: n/a | M19: Incorporated < 7 years | N19: Accumulated revenue ≤ RM5m | O19: Sdn Bhd only; owns tech IP; ≥2 directors; paid-up ≥ RM10k; tech-based venture | P19: Technology | Q19: Pitch deck (Cradle template); eligibility docs after shortlisting | R19: not stated | T19: =IF(S19="","",S19-TODAY()) | U19: Open (rolling) | V19: gms.cradle.com.my | W19: https://cradle.com.my/grants/cip-sprint/ | X19: Official | Z19: Not for the café. Relevant to YOUR team if you incorporate. | AA19: 46305
A20: MIDA-DIAF-ESG | B20: Domestic Investment Accelerator Fund – ESG Adoption (DIAF-ESG) | C20: MIDA | D20: Matching grant | F20: 500000 | G20: 50:50 matching, reimbursable | H20: n/a | I20: Malaysian-owned | J20: N | K20: N | L20: n/a | M20: not stated | N20: not stated | O20: SMEs and Mid-Tier Companies in manufacturing and selected services; ESG adoption | P20: Manufacturing, selected services | Q20: See Guidelines PDF (27 Apr 2026) | R20: 31 Oct 2026 | S20: 46326 | T20: =IF(S20="","",S20-TODAY()) | U20: Open — closes in 3 weeks | V20: Self-assessment at sustainability.mida.gov.my, then InvestMalaysia portal | W20: https://www.mida.gov.my/forms-and-guidelines/special-tax-incentives-under-penjana/the-domestic-investment-accelerator-fund-diaf-esg-adoption/ | X20: Official | Z20: Good test case for deadline alerts. | AA20: 46305
A21: HIJRAH-NIAGAPLUS | B21: Hijrah Selangor NIAGA PLUS | C21: Yayasan Hijrah Selangor (state) | D21: Microfinance | G21: Annual service charge (tawarruq); rate not published | H21: Up to 5 years | I21: Individual entrepreneurs who are registered voters and residents of Selangor | J21: N | K21: N | L21: 18–65 | M21: 1 year | N21: not stated | O21: Must vote and reside in Selangor; guarantor if required; for working capital, asset purchase and business premises renovation. Max RM50,000 reported by RinggitPlus (28 Jul 2026), not shown on the Hijrah site. Sister schemes: SURI PLUS (Selangor women), DANA Pantas, iTEKAD | P21: All | Q21: Copy of applicant's IC; latest 6 months bank statements; copy of SSM registration / PBT licence / agency or professional-body registration; copy of home or business premises utility bill; other supporting documents requested by Hijrah Selangor | R21: not stated | T21: =IF(S21="","",S21-TODAY()) | U21: Listed | V21: DANA PLUS app (guide at hijrahselangor.com/pages/cara-permohonan-pembiayaan) or any Hijrah Selangor branch; WhatsApp 016-912 1692 | W21: https://hijrahselangor.com/pages/niaga-plus | X21: Official (eligibility and documents are images on the page, read 2026-10-10) | Y21: VERIFY max amount and service-charge rate (not on Hijrah site) | Z21: Eligibility (age, Selangor voter and resident, ≥1 year operating, ≤5 years tenure) and documents now confirmed from the official page images. Still unconfirmed: maximum amount (RM50k comes only from RinggitPlus, 28 Jul 2026, https://ringgitplus.com/en/blog/business-loan/selangor-micro-financing-approval-now-takes-48-hours.html) and the service-charge rate, which the Hijrah site does not publish. Voter registration is not in the ledger: agent must ask. State-level scheme for Selangor businesses. | AA21: 46305

Sheet Summary
A1: Funding DB summary
A3: Programmes in DB | B3: =COUNTA(Programs!A2:A21)
A4: Bumiputera-only | B4: =COUNTIF(Programs!J2:J21,"Y")
A5: Women-only | B5: =COUNTIF(Programs!K2:K21,"Y")
A6: Need verification | B6: =COUNTIF(Programs!Y2:Y21,"VERIFY*")
A7: Closing within 60 days | B7: =COUNTIFS(Programs!T2:T21,">=0",Programs!T2:T21,"<=60")
